{"command": "code/do-segstats2nidm-perds ds001608", "system": {"cpu_total": 32, "memory_total": 1081801355264, "hostname": "typhon", "uid": 47521, "user": "yoh"}, "env": {}, "gpu": [{"index": "0", "name": "NVIDIA A100-PCIE-40GB", "bus_id": "00000000:31:00.0", "driver_version": "560.35.05", "memory.total": "40960 MiB", "compute_mode": "Default"}], "duct_version": "0.8.0", "schema_version": "0.2.0", "execution_summary": {"exit_code": 0, "command": "code/do-segstats2nidm-perds ds001608", "logs_prefix": ".duct/logs/2025.02.06T18.01.36-1537030_", "wall_clock_time": 335.7576415538788, "peak_rss": 639303680, "average_rss": 274137691.0920244, "peak_vsz": 1104332513280, "average_vsz": 93512492616.24551, "peak_pmem": 0.0, "average_pmem": 0.0, "peak_pcpu": 402.0, "average_pcpu": 137.96779141104307, "num_samples": 326, "num_reports": 7, "start_time": 1738882896.9195998, "end_time": 1738883232.6772413}, "output_paths": {"stdout": ".duct/logs/2025.02.06T18.01.36-1537030_stdout", "stderr": ".duct/logs/2025.02.06T18.01.36-1537030_stderr", "usage": ".duct/logs/2025.02.06T18.01.36-1537030_usage.json", "info": ".duct/logs/2025.02.06T18.01.36-1537030_info.json", "prefix": ".duct/logs/2025.02.06T18.01.36-1537030_"}}